{
  "transformer": {
    "kind": "transformer",
    "name": "azure-eventhubs:application-cloudevents",
    "title": "Azure Eventhubs (Application Cloudevents)",
    "description": "Adds CloudEvent headers to the Camel message with Azure Eventhubs consumer response details",
    "deprecated": false,
    "javaType": "org.apache.camel.component.azure.eventhubs.transform.EventHubsCloudEventDataTypeTransformer",
    "groupId": "org.apache.camel",
    "artifactId": "camel-azure-eventhubs",
    "version": "4.5.0-SNAPSHOT"
  }
}

