{
  "component": {
    "kind": "component",
    "name": "web3j",
    "title": "Web3j Ethereum Blockchain",
    "description": "Interact with Ethereum nodes using web3j client API.",
    "deprecated": false,
    "firstVersion": "2.22.0",
    "label": "blockchain",
    "javaType": "org.apache.camel.component.web3j.Web3jComponent",
    "supportLevel": "Stable",
    "groupId": "org.apache.camel",
    "artifactId": "camel-web3j",
    "version": "4.5.0-SNAPSHOT",
    "scheme": "web3j",
    "extendsScheme": "",
    "syntax": "web3j:nodeAddress",
    "async": false,
    "api": false,
    "consumerOnly": false,
    "producerOnly": false,
    "lenientProperties": false,
    "remote": true
  },
  "componentProperties": {
    "addresses": { "index": 0, "kind": "property", "displayName": "Addresses", "group": "common", "label": "common", "required": false, "type": "array", "javaType": "java.util.List<java.lang.String>", "deprecated": false, "autowired": false, "secret": false, "configurationClass": "org.apache.camel.component.web3j.Web3jConfiguration", "configurationField": "configuration", "description": "Contract address or a list of addresses." },
    "configuration": { "index": 1, "kind": "property", "displayName": "Configuration", "group": "common", "label": "", "required": false, "type": "object", "javaType": "org.apache.camel.component.web3j.Web3jConfiguration", "deprecated": false, "autowired": false, "secret": false, "description": "Default configuration" },
    "fromAddress": { "index": 2, "kind": "property", "displayName": "From Address", "group": "common", "label": "common", "required": false, "type": "string", "javaType": "java.lang.String", "deprecated": false, "autowired": false, "secret": false, "configurationClass": "org.apache.camel.component.web3j.Web3jConfiguration", "configurationField": "configuration", "description": "The address the transaction is send from" },
    "fromBlock": { "index": 3, "kind": "property", "displayName": "From Block", "group": "common", "label": "common", "required": false, "type": "string", "javaType": "java.lang.String", "deprecated": false, "autowired": false, "secret": false, "defaultValue": "latest", "configurationClass": "org.apache.camel.component.web3j.Web3jConfiguration", "configurationField": "configuration", "description": "The block number, or the string latest for the last mined block or pending, earliest for not yet mined transactions." },
    "fullTransactionObjects": { "index": 4, "kind": "property", "displayName": "Full Transaction Objects", "group": "common", "label": "common", "required": false, "type": "boolean", "javaType": "boolean", "deprecated": false, "autowired": false, "secret": false, "defaultValue": false, "configurationClass": "org.apache.camel.component.web3j.Web3jConfiguration", "configurationField": "configuration", "description": "If true it returns the full transaction objects, if false only the hashes of the transactions." },
    "gasLimit": { "index": 5, "kind": "property", "displayName": "Gas Limit", "group": "common", "label": "", "required": false, "type": "object", "javaType": "java.math.BigInteger", "deprecated": false, "autowired": false, "secret": false, "configurationClass": "org.apache.camel.component.web3j.Web3jConfiguration", "configurationField": "configuration", "description": "The maximum gas allowed in this block." },
    "privateFor": { "index": 6, "kind": "property", "displayName": "Private For", "group": "common", "label": "common", "required": false, "type": "array", "javaType": "java.util.List<java.lang.String>", "deprecated": false, "autowired": false, "secret": false, "configurationClass": "org.apache.camel.component.web3j.Web3jConfiguration", "configurationField": "configuration", "description": "A transaction privateFor nodes with public keys in a Quorum network" },
    "quorumAPI": { "index": 7, "kind": "property", "displayName": "Quorum API", "group": "common", "label": "common", "required": false, "type": "boolean", "javaType": "boolean", "deprecated": false, "autowired": false, "secret": false, "defaultValue": false, "configurationClass": "org.apache.camel.component.web3j.Web3jConfiguration", "configurationField": "configuration", "description": "If true, this will support Quorum API." },
    "toAddress": { "index": 8, "kind": "property", "displayName": "To Address", "group": "common", "label": "common", "required": false, "type": "string", "javaType": "java.lang.String", "deprecated": false, "autowired": false, "secret": false, "configurationClass": "org.apache.camel.component.web3j.Web3jConfiguration", "configurationField": "configuration", "description": "The address the transaction is directed to." },
    "toBlock": { "index": 9, "kind": "property", "displayName": "To Block", "group": "common", "label": "common", "required": false, "type": "string", "javaType": "java.lang.String", "deprecated": false, "autowired": false, "secret": false, "defaultValue": "latest", "configurationClass": "org.apache.camel.component.web3j.Web3jConfiguration", "configurationField": "configuration", "description": "The block number, or the string latest for the last mined block or pending, earliest for not yet mined transactions." },
    "topics": { "index": 10, "kind": "property", "displayName": "Topics", "group": "common", "label": "common", "required": false, "type": "string", "javaType": "java.lang.String", "deprecated": false, "autowired": false, "secret": false, "configurationClass": "org.apache.camel.component.web3j.Web3jConfiguration", "configurationField": "configuration", "description": "Topics are order-dependent. Each topic can also be a list of topics. Specify multiple topics separated by comma." },
    "web3j": { "index": 11, "kind": "property", "displayName": "Web3j", "group": "common", "label": "common", "required": false, "type": "object", "javaType": "org.web3j.protocol.Web3j", "deprecated": false, "autowired": false, "secret": false, "configurationClass": "org.apache.camel.component.web3j.Web3jConfiguration", "configurationField": "configuration", "description": "The preconfigured Web3j object." },
    "bridgeErrorHandler": { "index": 12, "kind": "property", "displayName": "Bridge Error Handler", "group": "consumer", "label": "consumer", "required": false, "type": "boolean", "javaType": "boolean", "deprecated": false, "autowired": false, "secret": false, "defaultValue": false, "description": "Allows for bridging the consumer to the Camel routing Error Handler, which mean any exceptions (if possible) occurred while the Camel consumer is trying to pickup incoming messages, or the likes, will now be processed as a message and handled by the routing Error Handler. Important: This is only possible if the 3rd party component allows Camel to be alerted if an exception was thrown. Some components handle this internally only, and therefore bridgeErrorHandler is not possible. In other situations we may improve the Camel component to hook into the 3rd party component and make this possible for future releases. By default the consumer will use the org.apache.camel.spi.ExceptionHandler to deal with exceptions, that will be logged at WARN or ERROR level and ignored." },
    "address": { "index": 13, "kind": "property", "displayName": "Address", "group": "producer", "label": "producer", "required": false, "type": "string", "javaType": "java.lang.String", "deprecated": false, "autowired": false, "secret": false, "configurationClass": "org.apache.camel.component.web3j.Web3jConfiguration", "configurationField": "configuration", "description": "Contract address." },
    "atBlock": { "index": 14, "kind": "property", "displayName": "At Block", "group": "producer", "label": "producer", "required": false, "type": "string", "javaType": "java.lang.String", "deprecated": false, "autowired": false, "secret": false, "defaultValue": "latest", "configurationClass": "org.apache.camel.component.web3j.Web3jConfiguration", "configurationField": "configuration", "description": "The block number, or the string latest for the last mined block or pending, earliest for not yet mined transactions." },
    "blockHash": { "index": 15, "kind": "property", "displayName": "Block Hash", "group": "producer", "label": "producer", "required": false, "type": "string", "javaType": "java.lang.String", "deprecated": false, "autowired": false, "secret": false, "configurationClass": "org.apache.camel.component.web3j.Web3jConfiguration", "configurationField": "configuration", "description": "Hash of the block where this transaction was in." },
    "clientId": { "index": 16, "kind": "property", "displayName": "Client Id", "group": "producer", "label": "producer", "required": false, "type": "string", "javaType": "java.lang.String", "deprecated": false, "autowired": false, "secret": false, "configurationClass": "org.apache.camel.component.web3j.Web3jConfiguration", "configurationField": "configuration", "description": "A random hexadecimal(32 bytes) ID identifying the client." },
    "data": { "index": 17, "kind": "property", "displayName": "Data", "group": "producer", "label": "producer", "required": false, "type": "string", "javaType": "java.lang.String", "deprecated": false, "autowired": false, "secret": false, "configurationClass": "org.apache.camel.component.web3j.Web3jConfiguration", "configurationField": "configuration", "description": "The compiled code of a contract OR the hash of the invoked method signature and encoded parameters." },
    "databaseName": { "index": 18, "kind": "property", "displayName": "Database Name", "group": "producer", "label": "producer", "required": false, "type": "string", "javaType": "java.lang.String", "deprecated": false, "autowired": false, "secret": false, "configurationClass": "org.apache.camel.component.web3j.Web3jConfiguration", "configurationField": "configuration", "description": "The local database name." },
    "filterId": { "index": 19, "kind": "property", "displayName": "Filter Id", "group": "producer", "label": "producer", "required": false, "type": "object", "javaType": "java.math.BigInteger", "deprecated": false, "autowired": false, "secret": false, "configurationClass": "org.apache.camel.component.web3j.Web3jConfiguration", "configurationField": "configuration", "description": "The filter id to use." },
    "gasPrice": { "index": 20, "kind": "property", "displayName": "Gas Price", "group": "producer", "label": "producer", "required": false, "type": "object", "javaType": "java.math.BigInteger", "deprecated": false, "autowired": false, "secret": false, "configurationClass": "org.apache.camel.component.web3j.Web3jConfiguration", "configurationField": "configuration", "description": "Gas price used for each paid gas." },
    "hashrate": { "index": 21, "kind": "property", "displayName": "Hashrate", "group": "producer", "label": "producer", "required": false, "type": "string", "javaType": "java.lang.String", "deprecated": false, "autowired": false, "secret": false, "configurationClass": "org.apache.camel.component.web3j.Web3jConfiguration", "configurationField": "configuration", "description": "A hexadecimal string representation (32 bytes) of the hash rate." },
    "headerPowHash": { "index": 22, "kind": "property", "displayName": "Header Pow Hash", "group": "producer", "label": "producer", "required": false, "type": "string", "javaType": "java.lang.String", "deprecated": false, "autowired": false, "secret": false, "configurationClass": "org.apache.camel.component.web3j.Web3jConfiguration", "configurationField": "configuration", "description": "The header's pow-hash (256 bits) used for submitting a proof-of-work solution." },
    "index": { "index": 23, "kind": "property", "displayName": "Index", "group": "producer", "label": "producer", "required": false, "type": "object", "javaType": "java.math.BigInteger", "deprecated": false, "autowired": false, "secret": false, "configurationClass": "org.apache.camel.component.web3j.Web3jConfiguration", "configurationField": "configuration", "description": "The transactions\/uncle index position in the block." },
    "keyName": { "index": 24, "kind": "property", "displayName": "Key Name", "group": "producer", "label": "producer", "required": false, "type": "string", "javaType": "java.lang.String", "deprecated": false, "autowired": false, "secret": false, "configurationClass": "org.apache.camel.component.web3j.Web3jConfiguration", "configurationField": "configuration", "description": "The key name in the database." },
    "lazyStartProducer": { "index": 25, "kind": "property", "displayName": "Lazy Start Producer", "group": "producer", "label": "producer", "required": false, "type": "boolean", "javaType": "boolean", "deprecated": false, "autowired": false, "secret": false, "defaultValue": false, "description": "Whether the producer should be started lazy (on the first message). By starting lazy you can use this to allow CamelContext and routes to startup in situations where a producer may otherwise fail during starting and cause the route to fail being started. By deferring this startup to be lazy then the startup failure can be handled during routing messages via Camel's routing error handlers. Beware that when the first message is processed then creating and starting the producer may take a little time and prolong the total processing time of the processing." },
    "mixDigest": { "index": 26, "kind": "property", "displayName": "Mix Digest", "group": "producer", "label": "producer", "required": false, "type": "string", "javaType": "java.lang.String", "deprecated": false, "autowired": false, "secret": false, "configurationClass": "org.apache.camel.component.web3j.Web3jConfiguration", "configurationField": "configuration", "description": "The mix digest (256 bits) used for submitting a proof-of-work solution." },
    "nonce": { "index": 27, "kind": "property", "displayName": "Nonce", "group": "producer", "label": "producer", "required": false, "type": "string", "javaType": "java.lang.String", "deprecated": false, "autowired": false, "secret": false, "configurationClass": "org.apache.camel.component.web3j.Web3jConfiguration", "configurationField": "configuration", "description": "The nonce found (64 bits) used for submitting a proof-of-work solution." },
    "operation": { "index": 28, "kind": "property", "displayName": "Operation", "group": "producer", "label": "producer", "required": false, "type": "string", "javaType": "java.lang.String", "deprecated": false, "autowired": false, "secret": false, "defaultValue": "transaction", "configurationClass": "org.apache.camel.component.web3j.Web3jConfiguration", "configurationField": "configuration", "description": "Operation to use." },
    "position": { "index": 29, "kind": "property", "displayName": "Position", "group": "producer", "label": "producer", "required": false, "type": "object", "javaType": "java.math.BigInteger", "deprecated": false, "autowired": false, "secret": false, "configurationClass": "org.apache.camel.component.web3j.Web3jConfiguration", "configurationField": "configuration", "description": "The transaction index position withing a block." },
    "priority": { "index": 30, "kind": "property", "displayName": "Priority", "group": "producer", "label": "producer", "required": false, "type": "object", "javaType": "java.math.BigInteger", "deprecated": false, "autowired": false, "secret": false, "configurationClass": "org.apache.camel.component.web3j.Web3jConfiguration", "configurationField": "configuration", "description": "The priority of a whisper message." },
    "sha3HashOfDataToSign": { "index": 31, "kind": "property", "displayName": "Sha3 Hash Of Data To Sign", "group": "producer", "label": "producer", "required": false, "type": "string", "javaType": "java.lang.String", "deprecated": false, "autowired": false, "secret": false, "configurationClass": "org.apache.camel.component.web3j.Web3jConfiguration", "configurationField": "configuration", "description": "Message to sign by calculating an Ethereum specific signature." },
    "signedTransactionData": { "index": 32, "kind": "property", "displayName": "Signed Transaction Data", "group": "producer", "label": "producer", "required": false, "type": "string", "javaType": "java.lang.String", "deprecated": false, "autowired": false, "secret": false, "configurationClass": "org.apache.camel.component.web3j.Web3jConfiguration", "configurationField": "configuration", "description": "The signed transaction data for a new message call transaction or a contract creation for signed transactions." },
    "sourceCode": { "index": 33, "kind": "property", "displayName": "Source Code", "group": "producer", "label": "producer", "required": false, "type": "string", "javaType": "java.lang.String", "deprecated": false, "autowired": false, "secret": false, "configurationClass": "org.apache.camel.component.web3j.Web3jConfiguration", "configurationField": "configuration", "description": "The source code to compile." },
    "transactionHash": { "index": 34, "kind": "property", "displayName": "Transaction Hash", "group": "producer", "label": "producer", "required": false, "type": "string", "javaType": "java.lang.String", "deprecated": false, "autowired": false, "secret": false, "configurationClass": "org.apache.camel.component.web3j.Web3jConfiguration", "configurationField": "configuration", "description": "The information about a transaction requested by transaction hash." },
    "ttl": { "index": 35, "kind": "property", "displayName": "Ttl", "group": "producer", "label": "producer", "required": false, "type": "object", "javaType": "java.math.BigInteger", "deprecated": false, "autowired": false, "secret": false, "configurationClass": "org.apache.camel.component.web3j.Web3jConfiguration", "configurationField": "configuration", "description": "The time to live in seconds of a whisper message." },
    "value": { "index": 36, "kind": "property", "displayName": "Value", "group": "producer", "label": "producer", "required": false, "type": "object", "javaType": "java.math.BigInteger", "deprecated": false, "autowired": false, "secret": false, "configurationClass": "org.apache.camel.component.web3j.Web3jConfiguration", "configurationField": "configuration", "description": "The value sent within a transaction." },
    "autowiredEnabled": { "index": 37, "kind": "property", "displayName": "Autowired Enabled", "group": "advanced", "label": "advanced", "required": false, "type": "boolean", "javaType": "boolean", "deprecated": false, "autowired": false, "secret": false, "defaultValue": true, "description": "Whether autowiring is enabled. This is used for automatic autowiring options (the option must be marked as autowired) by looking up in the registry to find if there is a single instance of matching type, which then gets configured on the component. This can be used for automatic configuring JDBC data sources, JMS connection factories, AWS Clients, etc." }
  },
  "headers": {
    "ETH_HASHRATE": { "index": 0, "kind": "header", "displayName": "", "group": "producer", "label": "producer", "required": false, "javaType": "String", "deprecated": false, "deprecationNote": "", "autowired": false, "secret": false, "description": "A hexadecimal string representation (32 bytes) of the hash rate.", "constantName": "org.apache.camel.component.web3j.Web3jConstants#ETH_HASHRATE" },
    "ID": { "index": 1, "kind": "header", "displayName": "", "group": "producer", "label": "producer", "required": false, "javaType": "Long", "deprecated": false, "deprecationNote": "", "autowired": false, "secret": false, "description": "The id", "constantName": "org.apache.camel.component.web3j.Web3jConstants#ID" },
    "AT_BLOCK": { "index": 2, "kind": "header", "displayName": "", "group": "producer", "label": "producer", "required": false, "javaType": "String", "deprecated": false, "deprecationNote": "", "autowired": false, "secret": false, "description": "The block number, or the string latest for the last mined block or pending, earliest for not yet mined transactions.", "constantName": "org.apache.camel.component.web3j.Web3jConstants#AT_BLOCK" },
    "ADDRESS": { "index": 3, "kind": "header", "displayName": "", "group": "producer", "label": "producer", "required": false, "javaType": "String", "deprecated": false, "deprecationNote": "", "autowired": false, "secret": false, "description": "Contract address.", "constantName": "org.apache.camel.component.web3j.Web3jConstants#ADDRESS" },
    "ADDRESSES": { "index": 4, "kind": "header", "displayName": "", "group": "producer", "label": "producer", "required": false, "javaType": "List<String>", "deprecated": false, "deprecationNote": "", "autowired": false, "secret": false, "description": "Contract address or a list of addresses.", "constantName": "org.apache.camel.component.web3j.Web3jConstants#ADDRESSES" },
    "FROM_ADDRESS": { "index": 5, "kind": "header", "displayName": "", "group": "producer", "label": "producer", "required": false, "javaType": "String", "deprecated": false, "deprecationNote": "", "autowired": false, "secret": false, "description": "The address the transaction is send from", "constantName": "org.apache.camel.component.web3j.Web3jConstants#FROM_ADDRESS" },
    "TO_ADDRESS": { "index": 6, "kind": "header", "displayName": "", "group": "producer", "label": "producer", "required": false, "javaType": "String", "deprecated": false, "deprecationNote": "", "autowired": false, "secret": false, "description": "The address the transaction is directed to", "constantName": "org.apache.camel.component.web3j.Web3jConstants#TO_ADDRESS" },
    "POSITION": { "index": 7, "kind": "header", "displayName": "", "group": "producer", "label": "producer", "required": false, "javaType": "String", "deprecated": false, "deprecationNote": "", "autowired": false, "secret": false, "description": "The transaction index position withing a block.", "constantName": "org.apache.camel.component.web3j.Web3jConstants#POSITION" },
    "BLOCK_HASH": { "index": 8, "kind": "header", "displayName": "", "group": "producer", "label": "producer", "required": false, "javaType": "String", "deprecated": false, "deprecationNote": "", "autowired": false, "secret": false, "description": "Hash of the block where this transaction was in.", "constantName": "org.apache.camel.component.web3j.Web3jConstants#BLOCK_HASH" },
    "TRANSACTION_HASH": { "index": 9, "kind": "header", "displayName": "", "group": "producer", "label": "producer", "required": false, "javaType": "String", "deprecated": false, "deprecationNote": "", "autowired": false, "secret": false, "description": "The information about a transaction requested by transaction hash.", "constantName": "org.apache.camel.component.web3j.Web3jConstants#TRANSACTION_HASH" },
    "SHA3_HASH_OF_DATA_TO_SIGN": { "index": 10, "kind": "header", "displayName": "", "group": "producer", "label": "producer", "required": false, "javaType": "String", "deprecated": false, "deprecationNote": "", "autowired": false, "secret": false, "description": "Message to sign by calculating an Ethereum specific signature.", "constantName": "org.apache.camel.component.web3j.Web3jConstants#SHA3_HASH_OF_DATA_TO_SIGN" },
    "SIGNED_TRANSACTION_DATA": { "index": 11, "kind": "header", "displayName": "", "group": "producer", "label": "producer", "required": false, "javaType": "String", "deprecated": false, "deprecationNote": "", "autowired": false, "secret": false, "description": "The signed transaction data for a new message call transaction or a contract creation for signed transactions.", "constantName": "org.apache.camel.component.web3j.Web3jConstants#SIGNED_TRANSACTION_DATA" },
    "FULL_TRANSACTION_OBJECTS": { "index": 12, "kind": "header", "displayName": "", "group": "producer", "label": "producer", "required": false, "javaType": "Boolean", "deprecated": false, "deprecationNote": "", "autowired": false, "secret": false, "description": "If true it returns the full transaction objects, if false only the hashes of the transactions.", "constantName": "org.apache.camel.component.web3j.Web3jConstants#FULL_TRANSACTION_OBJECTS" },
    "INDEX": { "index": 13, "kind": "header", "displayName": "", "group": "producer", "label": "producer", "required": false, "javaType": "String", "deprecated": false, "deprecationNote": "", "autowired": false, "secret": false, "description": "The transactions\/uncle index position in the block.", "constantName": "org.apache.camel.component.web3j.Web3jConstants#INDEX" },
    "SOURCE_CODE": { "index": 14, "kind": "header", "displayName": "", "group": "producer", "label": "producer", "required": false, "javaType": "String", "deprecated": false, "deprecationNote": "", "autowired": false, "secret": false, "description": "The source code to compile.", "constantName": "org.apache.camel.component.web3j.Web3jConstants#SOURCE_CODE" },
    "FILTER_ID": { "index": 15, "kind": "header", "displayName": "", "group": "producer", "label": "producer", "required": false, "javaType": "java.math.BigInteger", "deprecated": false, "deprecationNote": "", "autowired": false, "secret": false, "description": "The filter id to use.", "constantName": "org.apache.camel.component.web3j.Web3jConstants#FILTER_ID" },
    "DATABASE_NAME": { "index": 16, "kind": "header", "displayName": "", "group": "producer", "label": "producer", "required": false, "javaType": "String", "deprecated": false, "deprecationNote": "", "autowired": false, "secret": false, "description": "The local database name.", "constantName": "org.apache.camel.component.web3j.Web3jConstants#DATABASE_NAME" },
    "KEY_NAME": { "index": 17, "kind": "header", "displayName": "", "group": "producer", "label": "producer", "required": false, "javaType": "String", "deprecated": false, "deprecationNote": "", "autowired": false, "secret": false, "description": "The key name in the database.", "constantName": "org.apache.camel.component.web3j.Web3jConstants#KEY_NAME" },
    "NONCE": { "index": 18, "kind": "header", "displayName": "", "group": "producer", "label": "producer", "required": false, "javaType": "java.math.BigInteger", "deprecated": false, "deprecationNote": "", "autowired": false, "secret": false, "description": "The nonce found (64 bits) used for submitting a proof-of-work solution.", "constantName": "org.apache.camel.component.web3j.Web3jConstants#NONCE" },
    "HEADER_POW_HASH": { "index": 19, "kind": "header", "displayName": "", "group": "producer", "label": "producer", "required": false, "javaType": "String", "deprecated": false, "deprecationNote": "", "autowired": false, "secret": false, "description": "The header's pow-hash (256 bits) used for submitting a proof-of-work solution.", "constantName": "org.apache.camel.component.web3j.Web3jConstants#HEADER_POW_HASH" },
    "MIX_DIGEST": { "index": 20, "kind": "header", "displayName": "", "group": "producer", "label": "producer", "required": false, "javaType": "String", "deprecated": false, "deprecationNote": "", "autowired": false, "secret": false, "description": "The mix digest (256 bits) used for submitting a proof-of-work solution.", "constantName": "org.apache.camel.component.web3j.Web3jConstants#MIX_DIGEST" },
    "CLIENT_ID": { "index": 21, "kind": "header", "displayName": "", "group": "producer", "label": "producer", "required": false, "javaType": "String", "deprecated": false, "deprecationNote": "", "autowired": false, "secret": false, "description": "A random hexadecimal(32 bytes) ID identifying the client.", "constantName": "org.apache.camel.component.web3j.Web3jConstants#CLIENT_ID" },
    "GAS_PRICE": { "index": 22, "kind": "header", "displayName": "", "group": "producer", "label": "producer", "required": false, "javaType": "java.math.BigInteger", "deprecated": false, "deprecationNote": "", "autowired": false, "secret": false, "description": "Gas price used for each paid gas.", "constantName": "org.apache.camel.component.web3j.Web3jConstants#GAS_PRICE" },
    "GAS_LIMIT": { "index": 23, "kind": "header", "displayName": "", "group": "producer", "label": "producer", "required": false, "javaType": "java.math.BigInteger", "deprecated": false, "deprecationNote": "", "autowired": false, "secret": false, "description": "The maximum gas allowed in this block.", "constantName": "org.apache.camel.component.web3j.Web3jConstants#GAS_LIMIT" },
    "VALUE": { "index": 24, "kind": "header", "displayName": "", "group": "producer", "label": "producer", "required": false, "javaType": "java.math.BigInteger", "deprecated": false, "deprecationNote": "", "autowired": false, "secret": false, "description": "The value sent within a transaction.", "constantName": "org.apache.camel.component.web3j.Web3jConstants#VALUE" },
    "DATA": { "index": 25, "kind": "header", "displayName": "", "group": "producer", "label": "producer", "required": false, "javaType": "String", "deprecated": false, "deprecationNote": "", "autowired": false, "secret": false, "description": "The compiled code of a contract OR the hash of the invoked method signature and encoded parameters.", "constantName": "org.apache.camel.component.web3j.Web3jConstants#DATA" },
    "FROM_BLOCK": { "index": 26, "kind": "header", "displayName": "", "group": "producer", "label": "producer", "required": false, "javaType": "String", "deprecated": false, "deprecationNote": "", "autowired": false, "secret": false, "description": "The block number, or the string latest for the last mined block or pending, earliest for not yet mined transactions.", "constantName": "org.apache.camel.component.web3j.Web3jConstants#FROM_BLOCK" },
    "TO_BLOCK": { "index": 27, "kind": "header", "displayName": "", "group": "producer", "label": "producer", "required": false, "javaType": "String", "deprecated": false, "deprecationNote": "", "autowired": false, "secret": false, "description": "The block number, or the string latest for the last mined block or pending, earliest for not yet mined transactions.", "constantName": "org.apache.camel.component.web3j.Web3jConstants#TO_BLOCK" },
    "TOPICS": { "index": 28, "kind": "header", "displayName": "", "group": "producer", "label": "producer", "required": false, "javaType": "List<String>", "deprecated": false, "deprecationNote": "", "autowired": false, "secret": false, "description": "Topics are order-dependent. Each topic can also be a list of topics. Specify multiple topics separated by comma.", "constantName": "org.apache.camel.component.web3j.Web3jConstants#TOPICS" },
    "PRIORITY": { "index": 29, "kind": "header", "displayName": "", "group": "producer", "label": "producer", "required": false, "javaType": "java.math.BigInteger", "deprecated": false, "deprecationNote": "", "autowired": false, "secret": false, "description": "The priority of a whisper message.", "constantName": "org.apache.camel.component.web3j.Web3jConstants#PRIORITY" },
    "TTL": { "index": 30, "kind": "header", "displayName": "", "group": "producer", "label": "producer", "required": false, "javaType": "java.math.BigInteger", "deprecated": false, "deprecationNote": "", "autowired": false, "secret": false, "description": "The time to live in seconds of a whisper message.", "constantName": "org.apache.camel.component.web3j.Web3jConstants#TTL" },
    "PRIVATE_FOR": { "index": 31, "kind": "header", "displayName": "", "group": "producer", "label": "producer", "required": false, "javaType": "List<String>", "deprecated": false, "deprecationNote": "", "autowired": false, "secret": false, "description": "A transaction privateFor nodes with public keys in a Quorum network", "constantName": "org.apache.camel.component.web3j.Web3jConstants#PRIVATE_FOR" },
    "PRIVATE_FROM": { "index": 32, "kind": "header", "displayName": "", "group": "producer", "label": "producer", "required": false, "javaType": "String", "deprecated": false, "deprecationNote": "", "autowired": false, "secret": false, "description": "A transaction privateFrom", "constantName": "org.apache.camel.component.web3j.Web3jConstants#PRIVATE_FROM" },
    "ERROR_CODE": { "index": 33, "kind": "header", "displayName": "", "group": "producer", "label": "producer", "required": false, "javaType": "int", "deprecated": false, "deprecationNote": "", "autowired": false, "secret": false, "description": "The error code", "constantName": "org.apache.camel.component.web3j.Web3jConstants#ERROR_CODE" },
    "ERROR_DATA": { "index": 34, "kind": "header", "displayName": "", "group": "producer", "label": "producer", "required": false, "javaType": "String", "deprecated": false, "deprecationNote": "", "autowired": false, "secret": false, "description": "The error data", "constantName": "org.apache.camel.component.web3j.Web3jConstants#ERROR_DATA" },
    "ERROR_MESSAGE": { "index": 35, "kind": "header", "displayName": "", "group": "producer", "label": "producer", "required": false, "javaType": "String", "deprecated": false, "deprecationNote": "", "autowired": false, "secret": false, "description": "The error message", "constantName": "org.apache.camel.component.web3j.Web3jConstants#ERROR_MESSAGE" },
    "status": { "index": 36, "kind": "header", "displayName": "", "group": "consumer", "label": "consumer", "required": false, "javaType": "String", "deprecated": false, "deprecationNote": "", "autowired": false, "secret": false, "description": "The status of the operation", "constantName": "org.apache.camel.component.web3j.Web3jConstants#HEADER_STATUS" },
    "operation": { "index": 37, "kind": "header", "displayName": "", "group": "consumer", "label": "consumer", "required": false, "javaType": "String", "deprecated": false, "deprecationNote": "", "autowired": false, "secret": false, "description": "The operation", "constantName": "org.apache.camel.component.web3j.Web3jConstants#HEADER_OPERATION" }
  },
  "properties": {
    "nodeAddress": { "index": 0, "kind": "path", "displayName": "Node Address", "group": "common", "label": "", "required": true, "type": "string", "javaType": "java.lang.String", "deprecated": false, "deprecationNote": "", "autowired": false, "secret": false, "description": "Sets the node address used to communicate" },
    "addresses": { "index": 1, "kind": "parameter", "displayName": "Addresses", "group": "common", "label": "common", "required": false, "type": "array", "javaType": "java.util.List<java.lang.String>", "deprecated": false, "autowired": false, "secret": false, "configurationClass": "org.apache.camel.component.web3j.Web3jConfiguration", "configurationField": "configuration", "description": "Contract address or a list of addresses." },
    "fromAddress": { "index": 2, "kind": "parameter", "displayName": "From Address", "group": "common", "label": "common", "required": false, "type": "string", "javaType": "java.lang.String", "deprecated": false, "autowired": false, "secret": false, "configurationClass": "org.apache.camel.component.web3j.Web3jConfiguration", "configurationField": "configuration", "description": "The address the transaction is send from" },
    "fromBlock": { "index": 3, "kind": "parameter", "displayName": "From Block", "group": "common", "label": "common", "required": false, "type": "string", "javaType": "java.lang.String", "deprecated": false, "autowired": false, "secret": false, "defaultValue": "latest", "configurationClass": "org.apache.camel.component.web3j.Web3jConfiguration", "configurationField": "configuration", "description": "The block number, or the string latest for the last mined block or pending, earliest for not yet mined transactions." },
    "fullTransactionObjects": { "index": 4, "kind": "parameter", "displayName": "Full Transaction Objects", "group": "common", "label": "common", "required": false, "type": "boolean", "javaType": "boolean", "deprecated": false, "autowired": false, "secret": false, "defaultValue": false, "configurationClass": "org.apache.camel.component.web3j.Web3jConfiguration", "configurationField": "configuration", "description": "If true it returns the full transaction objects, if false only the hashes of the transactions." },
    "gasLimit": { "index": 5, "kind": "parameter", "displayName": "Gas Limit", "group": "common", "label": "", "required": false, "type": "object", "javaType": "java.math.BigInteger", "deprecated": false, "autowired": false, "secret": false, "configurationClass": "org.apache.camel.component.web3j.Web3jConfiguration", "configurationField": "configuration", "description": "The maximum gas allowed in this block." },
    "privateFor": { "index": 6, "kind": "parameter", "displayName": "Private For", "group": "common", "label": "common", "required": false, "type": "array", "javaType": "java.util.List<java.lang.String>", "deprecated": false, "autowired": false, "secret": false, "configurationClass": "org.apache.camel.component.web3j.Web3jConfiguration", "configurationField": "configuration", "description": "A transaction privateFor nodes with public keys in a Quorum network" },
    "quorumAPI": { "index": 7, "kind": "parameter", "displayName": "Quorum API", "group": "common", "label": "common", "required": false, "type": "boolean", "javaType": "boolean", "deprecated": false, "autowired": false, "secret": false, "defaultValue": false, "configurationClass": "org.apache.camel.component.web3j.Web3jConfiguration", "configurationField": "configuration", "description": "If true, this will support Quorum API." },
    "toAddress": { "index": 8, "kind": "parameter", "displayName": "To Address", "group": "common", "label": "common", "required": false, "type": "string", "javaType": "java.lang.String", "deprecated": false, "autowired": false, "secret": false, "configurationClass": "org.apache.camel.component.web3j.Web3jConfiguration", "configurationField": "configuration", "description": "The address the transaction is directed to." },
    "toBlock": { "index": 9, "kind": "parameter", "displayName": "To Block", "group": "common", "label": "common", "required": false, "type": "string", "javaType": "java.lang.String", "deprecated": false, "autowired": false, "secret": false, "defaultValue": "latest", "configurationClass": "org.apache.camel.component.web3j.Web3jConfiguration", "configurationField": "configuration", "description": "The block number, or the string latest for the last mined block or pending, earliest for not yet mined transactions." },
    "topics": { "index": 10, "kind": "parameter", "displayName": "Topics", "group": "common", "label": "common", "required": false, "type": "string", "javaType": "java.lang.String", "deprecated": false, "autowired": false, "secret": false, "configurationClass": "org.apache.camel.component.web3j.Web3jConfiguration", "configurationField": "configuration", "description": "Topics are order-dependent. Each topic can also be a list of topics. Specify multiple topics separated by comma." },
    "web3j": { "index": 11, "kind": "parameter", "displayName": "Web3j", "group": "common", "label": "common", "required": false, "type": "object", "javaType": "org.web3j.protocol.Web3j", "deprecated": false, "autowired": false, "secret": false, "configurationClass": "org.apache.camel.component.web3j.Web3jConfiguration", "configurationField": "configuration", "description": "The preconfigured Web3j object." },
    "bridgeErrorHandler": { "index": 12, "kind": "parameter", "displayName": "Bridge Error Handler", "group": "consumer (advanced)", "label": "consumer,advanced", "required": false, "type": "boolean", "javaType": "boolean", "deprecated": false, "autowired": false, "secret": false, "defaultValue": false, "description": "Allows for bridging the consumer to the Camel routing Error Handler, which mean any exceptions (if possible) occurred while the Camel consumer is trying to pickup incoming messages, or the likes, will now be processed as a message and handled by the routing Error Handler. Important: This is only possible if the 3rd party component allows Camel to be alerted if an exception was thrown. Some components handle this internally only, and therefore bridgeErrorHandler is not possible. In other situations we may improve the Camel component to hook into the 3rd party component and make this possible for future releases. By default the consumer will use the org.apache.camel.spi.ExceptionHandler to deal with exceptions, that will be logged at WARN or ERROR level and ignored." },
    "exceptionHandler": { "index": 13, "kind": "parameter", "displayName": "Exception Handler", "group": "consumer (advanced)", "label": "consumer,advanced", "required": false, "type": "object", "javaType": "org.apache.camel.spi.ExceptionHandler", "optionalPrefix": "consumer.", "deprecated": false, "autowired": false, "secret": false, "description": "To let the consumer use a custom ExceptionHandler. Notice if the option bridgeErrorHandler is enabled then this option is not in use. By default the consumer will deal with exceptions, that will be logged at WARN or ERROR level and ignored." },
    "exchangePattern": { "index": 14, "kind": "parameter", "displayName": "Exchange Pattern", "group": "consumer (advanced)", "label": "consumer,advanced", "required": false, "type": "object", "javaType": "org.apache.camel.ExchangePattern", "enum": [ "InOnly", "InOut" ], "deprecated": false, "autowired": false, "secret": false, "description": "Sets the exchange pattern when the consumer creates an exchange." },
    "address": { "index": 15, "kind": "parameter", "displayName": "Address", "group": "producer", "label": "producer", "required": false, "type": "string", "javaType": "java.lang.String", "deprecated": false, "autowired": false, "secret": false, "configurationClass": "org.apache.camel.component.web3j.Web3jConfiguration", "configurationField": "configuration", "description": "Contract address." },
    "atBlock": { "index": 16, "kind": "parameter", "displayName": "At Block", "group": "producer", "label": "producer", "required": false, "type": "string", "javaType": "java.lang.String", "deprecated": false, "autowired": false, "secret": false, "defaultValue": "latest", "configurationClass": "org.apache.camel.component.web3j.Web3jConfiguration", "configurationField": "configuration", "description": "The block number, or the string latest for the last mined block or pending, earliest for not yet mined transactions." },
    "blockHash": { "index": 17, "kind": "parameter", "displayName": "Block Hash", "group": "producer", "label": "producer", "required": false, "type": "string", "javaType": "java.lang.String", "deprecated": false, "autowired": false, "secret": false, "configurationClass": "org.apache.camel.component.web3j.Web3jConfiguration", "configurationField": "configuration", "description": "Hash of the block where this transaction was in." },
    "clientId": { "index": 18, "kind": "parameter", "displayName": "Client Id", "group": "producer", "label": "producer", "required": false, "type": "string", "javaType": "java.lang.String", "deprecated": false, "autowired": false, "secret": false, "configurationClass": "org.apache.camel.component.web3j.Web3jConfiguration", "configurationField": "configuration", "description": "A random hexadecimal(32 bytes) ID identifying the client." },
    "data": { "index": 19, "kind": "parameter", "displayName": "Data", "group": "producer", "label": "producer", "required": false, "type": "string", "javaType": "java.lang.String", "deprecated": false, "autowired": false, "secret": false, "configurationClass": "org.apache.camel.component.web3j.Web3jConfiguration", "configurationField": "configuration", "description": "The compiled code of a contract OR the hash of the invoked method signature and encoded parameters." },
    "databaseName": { "index": 20, "kind": "parameter", "displayName": "Database Name", "group": "producer", "label": "producer", "required": false, "type": "string", "javaType": "java.lang.String", "deprecated": false, "autowired": false, "secret": false, "configurationClass": "org.apache.camel.component.web3j.Web3jConfiguration", "configurationField": "configuration", "description": "The local database name." },
    "filterId": { "index": 21, "kind": "parameter", "displayName": "Filter Id", "group": "producer", "label": "producer", "required": false, "type": "object", "javaType": "java.math.BigInteger", "deprecated": false, "autowired": false, "secret": false, "configurationClass": "org.apache.camel.component.web3j.Web3jConfiguration", "configurationField": "configuration", "description": "The filter id to use." },
    "gasPrice": { "index": 22, "kind": "parameter", "displayName": "Gas Price", "group": "producer", "label": "producer", "required": false, "type": "object", "javaType": "java.math.BigInteger", "deprecated": false, "autowired": false, "secret": false, "configurationClass": "org.apache.camel.component.web3j.Web3jConfiguration", "configurationField": "configuration", "description": "Gas price used for each paid gas." },
    "hashrate": { "index": 23, "kind": "parameter", "displayName": "Hashrate", "group": "producer", "label": "producer", "required": false, "type": "string", "javaType": "java.lang.String", "deprecated": false, "autowired": false, "secret": false, "configurationClass": "org.apache.camel.component.web3j.Web3jConfiguration", "configurationField": "configuration", "description": "A hexadecimal string representation (32 bytes) of the hash rate." },
    "headerPowHash": { "index": 24, "kind": "parameter", "displayName": "Header Pow Hash", "group": "producer", "label": "producer", "required": false, "type": "string", "javaType": "java.lang.String", "deprecated": false, "autowired": false, "secret": false, "configurationClass": "org.apache.camel.component.web3j.Web3jConfiguration", "configurationField": "configuration", "description": "The header's pow-hash (256 bits) used for submitting a proof-of-work solution." },
    "index": { "index": 25, "kind": "parameter", "displayName": "Index", "group": "producer", "label": "producer", "required": false, "type": "object", "javaType": "java.math.BigInteger", "deprecated": false, "autowired": false, "secret": false, "configurationClass": "org.apache.camel.component.web3j.Web3jConfiguration", "configurationField": "configuration", "description": "The transactions\/uncle index position in the block." },
    "keyName": { "index": 26, "kind": "parameter", "displayName": "Key Name", "group": "producer", "label": "producer", "required": false, "type": "string", "javaType": "java.lang.String", "deprecated": false, "autowired": false, "secret": false, "configurationClass": "org.apache.camel.component.web3j.Web3jConfiguration", "configurationField": "configuration", "description": "The key name in the database." },
    "mixDigest": { "index": 27, "kind": "parameter", "displayName": "Mix Digest", "group": "producer", "label": "producer", "required": false, "type": "string", "javaType": "java.lang.String", "deprecated": false, "autowired": false, "secret": false, "configurationClass": "org.apache.camel.component.web3j.Web3jConfiguration", "configurationField": "configuration", "description": "The mix digest (256 bits) used for submitting a proof-of-work solution." },
    "nonce": { "index": 28, "kind": "parameter", "displayName": "Nonce", "group": "producer", "label": "producer", "required": false, "type": "string", "javaType": "java.lang.String", "deprecated": false, "autowired": false, "secret": false, "configurationClass": "org.apache.camel.component.web3j.Web3jConfiguration", "configurationField": "configuration", "description": "The nonce found (64 bits) used for submitting a proof-of-work solution." },
    "operation": { "index": 29, "kind": "parameter", "displayName": "Operation", "group": "producer", "label": "producer", "required": false, "type": "string", "javaType": "java.lang.String", "deprecated": false, "autowired": false, "secret": false, "defaultValue": "transaction", "configurationClass": "org.apache.camel.component.web3j.Web3jConfiguration", "configurationField": "configuration", "description": "Operation to use." },
    "position": { "index": 30, "kind": "parameter", "displayName": "Position", "group": "producer", "label": "producer", "required": false, "type": "object", "javaType": "java.math.BigInteger", "deprecated": false, "autowired": false, "secret": false, "configurationClass": "org.apache.camel.component.web3j.Web3jConfiguration", "configurationField": "configuration", "description": "The transaction index position withing a block." },
    "priority": { "index": 31, "kind": "parameter", "displayName": "Priority", "group": "producer", "label": "producer", "required": false, "type": "object", "javaType": "java.math.BigInteger", "deprecated": false, "autowired": false, "secret": false, "configurationClass": "org.apache.camel.component.web3j.Web3jConfiguration", "configurationField": "configuration", "description": "The priority of a whisper message." },
    "sha3HashOfDataToSign": { "index": 32, "kind": "parameter", "displayName": "Sha3 Hash Of Data To Sign", "group": "producer", "label": "producer", "required": false, "type": "string", "javaType": "java.lang.String", "deprecated": false, "autowired": false, "secret": false, "configurationClass": "org.apache.camel.component.web3j.Web3jConfiguration", "configurationField": "configuration", "description": "Message to sign by calculating an Ethereum specific signature." },
    "signedTransactionData": { "index": 33, "kind": "parameter", "displayName": "Signed Transaction Data", "group": "producer", "label": "producer", "required": false, "type": "string", "javaType": "java.lang.String", "deprecated": false, "autowired": false, "secret": false, "configurationClass": "org.apache.camel.component.web3j.Web3jConfiguration", "configurationField": "configuration", "description": "The signed transaction data for a new message call transaction or a contract creation for signed transactions." },
    "sourceCode": { "index": 34, "kind": "parameter", "displayName": "Source Code", "group": "producer", "label": "producer", "required": false, "type": "string", "javaType": "java.lang.String", "deprecated": false, "autowired": false, "secret": false, "configurationClass": "org.apache.camel.component.web3j.Web3jConfiguration", "configurationField": "configuration", "description": "The source code to compile." },
    "transactionHash": { "index": 35, "kind": "parameter", "displayName": "Transaction Hash", "group": "producer", "label": "producer", "required": false, "type": "string", "javaType": "java.lang.String", "deprecated": false, "autowired": false, "secret": false, "configurationClass": "org.apache.camel.component.web3j.Web3jConfiguration", "configurationField": "configuration", "description": "The information about a transaction requested by transaction hash." },
    "ttl": { "index": 36, "kind": "parameter", "displayName": "Ttl", "group": "producer", "label": "producer", "required": false, "type": "object", "javaType": "java.math.BigInteger", "deprecated": false, "autowired": false, "secret": false, "configurationClass": "org.apache.camel.component.web3j.Web3jConfiguration", "configurationField": "configuration", "description": "The time to live in seconds of a whisper message." },
    "value": { "index": 37, "kind": "parameter", "displayName": "Value", "group": "producer", "label": "producer", "required": false, "type": "object", "javaType": "java.math.BigInteger", "deprecated": false, "autowired": false, "secret": false, "configurationClass": "org.apache.camel.component.web3j.Web3jConfiguration", "configurationField": "configuration", "description": "The value sent within a transaction." },
    "lazyStartProducer": { "index": 38, "kind": "parameter", "displayName": "Lazy Start Producer", "group": "producer (advanced)", "label": "producer,advanced", "required": false, "type": "boolean", "javaType": "boolean", "deprecated": false, "autowired": false, "secret": false, "defaultValue": false, "description": "Whether the producer should be started lazy (on the first message). By starting lazy you can use this to allow CamelContext and routes to startup in situations where a producer may otherwise fail during starting and cause the route to fail being started. By deferring this startup to be lazy then the startup failure can be handled during routing messages via Camel's routing error handlers. Beware that when the first message is processed then creating and starting the producer may take a little time and prolong the total processing time of the processing." }
  }
}
