{
  "$schema": "http://json-schema.org/draft-07/schema#",
  "$id": "https://schema.ocsf.io/1.7.0/objects/dns_query",
  "title": "DnsQuery",
  "type": "object",
  "javaType": "org.apache.camel.dataformat.ocsf.model.DnsQuery",
  "additionalProperties": true,
  "properties": {
    "type": {
      "type": "string",
      "title": "Resource Record Type"
    },
    "hostname": {
      "type": "string",
      "title": "Hostname"
    },
    "class": {
      "type": "string",
      "title": "Resource Record Class"
    },
    "opcode": {
      "type": "string",
      "title": "DNS Opcode"
    },
    "opcode_id": {
      "type": "integer",
      "title": "DNS Opcode ID"
    },
    "packet_uid": {
      "type": "integer",
      "title": "Packet UID"
    }
  },
  "description": "The DNS Query object."
}