{
  "bean": {
    "kind": "bean",
    "name": "ZooKeeperClusterService",
    "javaType": "org.apache.camel.component.zookeeper.cluster.ZooKeeperClusterService",
    "interfaceType": "org.apache.camel.cluster.CamelClusterService",
    "title": "Zoo Keeper Cluster Service",
    "description": "ZooKeeper based cluster locking",
    "deprecated": false,
    "groupId": "org.apache.camel",
    "artifactId": "camel-zookeeper",
    "version": "4.19.0-SNAPSHOT",
    "properties": { "nodes": { "index": 0, "kind": "property", "displayName": "Nodes", "required": true, "type": "string", "javaType": "java.lang.String", "deprecated": false, "autowired": false, "secret": false, "description": "The Zookeeper server hosts (multiple servers can be separated by comma)" }, "basePath": { "index": 1, "kind": "property", "displayName": "Base Path", "required": true, "type": "string", "javaType": "java.lang.String", "deprecated": false, "autowired": false, "secret": false, "description": "The base path to store in ZooKeeper" }, "id": { "index": 2, "kind": "property", "displayName": "Id", "required": true, "type": "string", "javaType": "java.lang.String", "deprecated": false, "autowired": false, "secret": false, "description": "Node id" }, "namespace": { "index": 3, "kind": "property", "displayName": "Namespace", "required": false, "type": "string", "javaType": "java.lang.String", "deprecated": false, "autowired": false, "secret": false, "description": "ZooKeeper namespace. If a namespace is set here, all paths will get pre-pended with the namespace" }, "reconnectMaxRetries": { "index": 4, "kind": "property", "displayName": "Reconnect Max Retries", "required": false, "type": "integer", "javaType": "int", "deprecated": false, "autowired": false, "secret": false, "defaultValue": 3, "description": "Max number of times to retry" }, "reconnectBaseSleepTime": { "index": 5, "kind": "property", "displayName": "Reconnect Base Sleep Time", "required": false, "type": "integer", "javaType": "long", "deprecated": false, "autowired": false, "secret": false, "defaultValue": 1000, "description": "Initial amount of time (millis) to wait between retries" }, "reconnectMaxSleepTime": { "index": 6, "kind": "property", "displayName": "Reconnect Max Sleep Time", "required": false, "type": "integer", "javaType": "long", "deprecated": false, "autowired": false, "secret": false, "description": "Max time (millis) to sleep on each retry" }, "sessionTimeout": { "index": 7, "kind": "property", "displayName": "Session Timeout", "required": false, "type": "integer", "javaType": "long", "deprecated": false, "autowired": false, "secret": false, "defaultValue": 60000, "description": "Session timeout (millis)" }, "connectTimeout": { "index": 8, "kind": "property", "displayName": "Connect Timeout", "required": false, "type": "integer", "javaType": "long", "deprecated": false, "autowired": false, "secret": false, "defaultValue": 15000, "description": "Connect timeout (millis)" }, "maxCloseWait": { "index": 9, "kind": "property", "displayName": "Max Close Wait", "required": false, "type": "integer", "javaType": "long", "deprecated": false, "autowired": false, "secret": false, "defaultValue": 1000, "description": "Time to wait (millis) during close to join background threads" }, "retryPolicy": { "index": 10, "kind": "property", "displayName": "Retry Policy", "label": "advanced", "required": false, "type": "object", "javaType": "org.apache.curator.RetryPolicy", "deprecated": false, "autowired": false, "secret": false, "description": "To use a custom retry policy implementation" } }
  }
}

