{
  "model": {
    "kind": "model",
    "name": "throwException",
    "title": "Throw Exception",
    "description": "Throws an exception",
    "deprecated": false,
    "label": "error",
    "javaType": "org.apache.camel.model.ThrowExceptionDefinition",
    "abstract": false,
    "input": true,
    "output": false
  },
  "properties": {
    "id": { "index": 0, "kind": "attribute", "displayName": "Id", "group": "common", "required": false, "type": "string", "javaType": "java.lang.String", "deprecated": false, "autowired": false, "secret": false, "description": "Sets the id of this node" },
    "note": { "index": 1, "kind": "attribute", "displayName": "Note", "group": "common", "required": false, "type": "string", "javaType": "java.lang.String", "deprecated": false, "autowired": false, "secret": false, "description": "Sets the note of this node" },
    "description": { "index": 2, "kind": "attribute", "displayName": "Description", "group": "common", "required": false, "type": "string", "javaType": "java.lang.String", "deprecated": false, "autowired": false, "secret": false, "description": "Sets the description of this node" },
    "disabled": { "index": 3, "kind": "attribute", "displayName": "Disabled", "group": "advanced", "label": "advanced", "required": false, "type": "boolean", "javaType": "java.lang.Boolean", "deprecated": false, "autowired": false, "secret": false, "defaultValue": false, "description": "Disables this EIP from the route." },
    "message": { "index": 4, "kind": "attribute", "displayName": "Message", "group": "common", "required": false, "type": "string", "javaType": "java.lang.String", "deprecated": false, "autowired": false, "secret": false, "description": "To create a new exception instance and use the given message as caused message (supports simple language)" },
    "exceptionType": { "index": 5, "kind": "attribute", "displayName": "Exception Type", "group": "common", "required": false, "type": "string", "javaType": "java.lang.String", "deprecated": false, "autowired": false, "secret": false, "description": "The class of the exception to create using the message." },
    "ref": { "index": 6, "kind": "attribute", "displayName": "Ref", "group": "advanced", "label": "advanced", "required": false, "type": "string", "javaType": "java.lang.String", "deprecated": false, "autowired": false, "secret": false, "description": "Reference to the exception instance to lookup from the registry to throw" }
  }
}
